tests/__init__.py
tests/_pusher/__init__.py
tests/_pusher/client.py
tests/bgc/__init__.py
tests/bgc/client.py
tests/bgc/us_one_trace.py
tests/compass/__init__.py
tests/compass/client.py
tests/iei/__init__.py
tests/iei/client.py
tests/laniidae/__init__.py
tests/laniidae/create_new_user.py
tetrapod/__init__.py
tetrapod/factories.py
tetrapod/is_type.py
tetrapod/pipelines.py
tetrapod/regex.py
tetrapod/s_dict.py
tetrapod/string.py
tetrapod/bgc/__init__.py
tetrapod/bgc/client.py
tetrapod/bgc/connection.py
tetrapod/bgc/endpoint.py
tetrapod/bgc/exceptions.py
tetrapod/bgc/factories/__init__.py
tetrapod/bgc/factories/bgc.py
tetrapod/bgc/factories/us_one_trace.py
tetrapod/bgc/factories/us_one_validate.py
tetrapod/compass/__init__.py
tetrapod/compass/build_xml.py
tetrapod/compass/client.py
tetrapod/compass/exceptions.py
tetrapod/iei/__init__.py
tetrapod/iei/client.py
tetrapod/iei/exceptions.py
tetrapod/iei/pipelines.py
tetrapod/iei/factories/__init__.py
tetrapod/iei/factories/fact.py
tetrapod/iei/factories/iei.py
tetrapod/laniidae/__init__.py
tetrapod/laniidae/client.py
tetrapod/laniidae/endpoints.py
tetrapod/laniidae/exceptions.py
tetrapod/laniidae/response.py
tetrapod/pusher/__init__.py
tetrapod/pusher/client.py
tetrapod-1.6.3.dist-info/METADATA
tetrapod-1.6.3.dist-info/RECORD
tetrapod-1.6.3.dist-info/WHEEL
tetrapod-1.6.3.dist-info/top_level.txt
