Metadata-Version: 2.1
Name: tetrapod
Version: 1.6.3
Summary: UNKNOWN
Home-page: UNKNOWN
Author: UNKNOWN
Author-email: UNKNOWN
License: UNKNOWN
Platform: UNKNOWN
Classifier: Environment :: Console
Classifier: Intended Audience :: Developers
Classifier: Programming Language :: Python
Requires-Dist: xmltodict (>=0.11.0)
Requires-Dist: pusher (==2.1.2)
Requires-Dist: chibi (==0.4.0.5)
